[
{"urls": ["https://db.idrowiki.org/klasik/map/beach_dun", "https://db.idrowiki.org/klasik/map/beach_dun2", "https://db.idrowiki.org/klasik/map/beach_dun3", "https://db.idrowiki.org/klasik/map/cmd_fild01", "https://db.idrowiki.org/klasik/map/cmd_fild02", "https://db.idrowiki.org/klasik/map/cmd_fild03", "https://db.idrowiki.org/klasik/map/cmd_fild04"]},
{"urls": []},
{"urls": ["https://db.idrowiki.org/klasik/map/anthell01", "https://db.idrowiki.org/klasik/map/anthell02"]},
{"urls": []},
{"urls": ["https://db.idrowiki.org/klasik/map/alde_dun01", "https://db.idrowiki.org/klasik/map/alde_dun02", "https://db.idrowiki.org/klasik/map/alde_dun03", "https://db.idrowiki.org/klasik/map/alde_dun04"]},
{"urls": []},
{"urls": []},
{"urls": ["https://db.idrowiki.org/klasik/map/cmd_fild05", "https://db.idrowiki.org/klasik/map/cmd_fild06", "https://db.idrowiki.org/klasik/map/cmd_fild07", "https://db.idrowiki.org/klasik/map/cmd_fild08", "https://db.idrowiki.org/klasik/map/cmd_fild09", "https://db.idrowiki.org/klasik/map/c_tower1", "https://db.idrowiki.org/klasik/map/c_tower2", "https://db.idrowiki.org/klasik/map/c_tower3", "https://db.idrowiki.org/klasik/map/c_tower4"]},
{"urls": []},
{"urls": ["https://db.idrowiki.org/klasik/map/gef_fild04", "https://db.idrowiki.org/klasik/map/gef_fild05", "https://db.idrowiki.org/klasik/map/gef_fild06", "https://db.idrowiki.org/klasik/map/gef_fild07", "https://db.idrowiki.org/klasik/map/gef_fild08", "https://db.idrowiki.org/klasik/map/gef_fild09", "https://db.idrowiki.org/klasik/map/gef_fild10", "https://db.idrowiki.org/klasik/map/gef_fild11", "https://db.idrowiki.org/klasik/map/gef_fild12", "https://db.idrowiki.org/klasik/map/gef_fild13", "https://db.idrowiki.org/klasik/map/gef_fild14", "https://db.idrowiki.org/klasik/map/glast_01"]},
{"urls": ["https://db.idrowiki.org/klasik/map/gef_dun00", "https://db.idrowiki.org/klasik/map/gef_dun01", "https://db.idrowiki.org/klasik/map/gef_dun02", "https://db.idrowiki.org/klasik/map/gef_dun03", "https://db.idrowiki.org/klasik/map/gef_fild00", "https://db.idrowiki.org/klasik/map/gef_fild01", "https://db.idrowiki.org/klasik/map/gef_fild02", "https://db.idrowiki.org/klasik/map/gef_fild03"]},
{"urls": ["https://db.idrowiki.org/klasik/map/in_sphinx1", "https://db.idrowiki.org/klasik/map/in_sphinx2", "https://db.idrowiki.org/klasik/map/in_sphinx3", "https://db.idrowiki.org/klasik/map/in_sphinx4", "https://db.idrowiki.org/klasik/map/in_sphinx5"]},
{"urls": []},
{"urls": ["https://db.idrowiki.org/klasik/map/gl_cas01", "https://db.idrowiki.org/klasik/map/gl_cas02", "https://db.idrowiki.org/klasik/map/gl_church", "https://db.idrowiki.org/klasik/map/gl_chyard", "https://db.idrowiki.org/klasik/map/gl_dun01", "https://db.idrowiki.org/klasik/map/gl_dun02", "https://db.idrowiki.org/klasik/map/gl_in01", "https://db.idrowiki.org/klasik/map/gl_knt01", "https://db.idrowiki.org/klasik/map/gl_knt02", "https://db.idrowiki.org/klasik/map/gl_prison", "https://db.idrowiki.org/klasik/map/gl_prison1", "https://db.idrowiki.org/klasik/map/gl_sew01", "https://db.idrowiki.org/klasik/map/gl_sew02", "https://db.idrowiki.org/klasik/map/gl_sew03", "https://db.idrowiki.org/klasik/map/gl_sew04", "https://db.idrowiki.org/klasik/map/gl_step"]},
{"urls": ["https://db.idrowiki.org/klasik/map/iz_dun00", "https://db.idrowiki.org/klasik/map/iz_dun01", "https://db.idrowiki.org/klasik/map/iz_dun02", "https://db.idrowiki.org/klasik/map/iz_dun03", "https://db.idrowiki.org/klasik/map/iz_dun04"]},
{"urls": []},
{"urls": []},
{"urls": []},
{"urls": []},
{"urls": ["https://db.idrowiki.org/klasik/map/mjolnir_01", "https://db.idrowiki.org/klasik/map/mjolnir_02", "https://db.idrowiki.org/klasik/map/mjolnir_03", "https://db.idrowiki.org/klasik/map/mjolnir_04", "https://db.idrowiki.org/klasik/map/mjolnir_05", "https://db.idrowiki.org/klasik/map/mjolnir_06", "https://db.idrowiki.org/klasik/map/mjolnir_07", "https://db.idrowiki.org/klasik/map/mjolnir_08", "https://db.idrowiki.org/klasik/map/mjolnir_09", "https://db.idrowiki.org/klasik/map/mjolnir_10", "https://db.idrowiki.org/klasik/map/mjolnir_11", "https://db.idrowiki.org/klasik/map/mjolnir_12", "https://db.idrowiki.org/klasik/map/mjo_dun01", "https://db.idrowiki.org/klasik/map/mjo_dun02", "https://db.idrowiki.org/klasik/map/mjo_dun03"]},
{"urls": ["https://db.idrowiki.org/klasik/map/moc_fild01", "https://db.idrowiki.org/klasik/map/moc_fild01", "https://db.idrowiki.org/klasik/map/moc_fild02", "https://db.idrowiki.org/klasik/map/moc_fild02", "https://db.idrowiki.org/klasik/map/moc_fild03", "https://db.idrowiki.org/klasik/map/moc_fild03", "https://db.idrowiki.org/klasik/map/moc_fild04", "https://db.idrowiki.org/klasik/map/moc_fild04", "https://db.idrowiki.org/klasik/map/moc_fild05", "https://db.idrowiki.org/klasik/map/moc_fild06", "https://db.idrowiki.org/klasik/map/moc_fild07", "https://db.idrowiki.org/klasik/map/moc_fild08", "https://db.idrowiki.org/klasik/map/moc_fild09", "https://db.idrowiki.org/klasik/map/moc_fild10", "https://db.idrowiki.org/klasik/map/moc_fild11", "https://db.idrowiki.org/klasik/map/moc_fild12", "https://db.idrowiki.org/klasik/map/moc_fild13", "https://db.idrowiki.org/klasik/map/moc_fild14", "https://db.idrowiki.org/klasik/map/moc_fild15", "https://db.idrowiki.org/klasik/map/moc_fild16", "https://db.idrowiki.org/klasik/map/moc_fild17", "https://db.idrowiki.org/klasik/map/moc_fild18"]},
{"urls": ["https://db.idrowiki.org/klasik/map/moc_pryd01", "https://db.idrowiki.org/klasik/map/moc_pryd02", "https://db.idrowiki.org/klasik/map/moc_pryd03", "https://db.idrowiki.org/klasik/map/moc_pryd04", "https://db.idrowiki.org/klasik/map/moc_pryd05", "https://db.idrowiki.org/klasik/map/moc_pryd06"]},
{"urls": []},
{"urls": []},
{"urls": ["https://db.idrowiki.org/klasik/map/orcsdun01", "https://db.idrowiki.org/klasik/map/orcsdun02"]},
{"urls": ["https://db.idrowiki.org/klasik/map/pay_dun00", "https://db.idrowiki.org/klasik/map/pay_dun01", "https://db.idrowiki.org/klasik/map/pay_dun02", "https://db.idrowiki.org/klasik/map/pay_dun03", "https://db.idrowiki.org/klasik/map/pay_dun04", "https://db.idrowiki.org/klasik/map/pay_fild01", "https://db.idrowiki.org/klasik/map/pay_fild02", "https://db.idrowiki.org/klasik/map/pay_fild03", "https://db.idrowiki.org/klasik/map/pay_fild04", "https://db.idrowiki.org/klasik/map/pay_fild05", "https://db.idrowiki.org/klasik/map/pay_fild06", "https://db.idrowiki.org/klasik/map/pay_fild07", "https://db.idrowiki.org/klasik/map/pay_fild08", "https://db.idrowiki.org/klasik/map/pay_fild09", "https://db.idrowiki.org/klasik/map/pay_fild10", "https://db.idrowiki.org/klasik/map/pay_fild11"]},
{"urls": ["https://db.idrowiki.org/klasik/map/prt_fild00", "https://db.idrowiki.org/klasik/map/prt_fild00"]},
{"urls": ["https://db.idrowiki.org/klasik/map/prt_fild01", "https://db.idrowiki.org/klasik/map/prt_fild01", "https://db.idrowiki.org/klasik/map/prt_fild02", "https://db.idrowiki.org/klasik/map/prt_fild03", "https://db.idrowiki.org/klasik/map/prt_fild03", "https://db.idrowiki.org/klasik/map/prt_fild04", "https://db.idrowiki.org/klasik/map/prt_fild04", "https://db.idrowiki.org/klasik/map/prt_fild05", "https://db.idrowiki.org/klasik/map/prt_fild05", "https://db.idrowiki.org/klasik/map/prt_fild06", "https://db.idrowiki.org/klasik/map/prt_fild07", "https://db.idrowiki.org/klasik/map/prt_fild08", "https://db.idrowiki.org/klasik/map/prt_fild09", "https://db.idrowiki.org/klasik/map/prt_fild10", "https://db.idrowiki.org/klasik/map/prt_fild11", "https://db.idrowiki.org/klasik/map/prt_maze01"]},
{"urls": ["https://db.idrowiki.org/klasik/map/prt_maze03", "https://db.idrowiki.org/klasik/map/prt_sewb1", "https://db.idrowiki.org/klasik/map/prt_sewb2", "https://db.idrowiki.org/klasik/map/prt_sewb3", "https://db.idrowiki.org/klasik/map/prt_sewb4"]},
{"urls": []},
{"urls": []},
{"urls": []},
{"urls": []},
{"urls": []},
{"urls": []},
{"urls": ["https://db.idrowiki.org/klasik/map/treasure01", "https://db.idrowiki.org/klasik/map/treasure02"]},
{"urls": ["https://db.idrowiki.org/klasik/map/tur_dun01", "https://db.idrowiki.org/klasik/map/tur_dun02", "https://db.idrowiki.org/klasik/map/tur_dun03", "https://db.idrowiki.org/klasik/map/tur_dun04"]},
{"urls": []},
{"urls": []},
{"urls": []}
]